rest_helpers/__init__.py
rest_helpers/binding.py
rest_helpers/framework_adapter.py
rest_helpers/jsonapi_objects.py
rest_helpers/responses.py
rest_helpers/rest_exceptions.py
rest_helpers/rest_helper_context.py
rest_helpers/routes.py
rest_helpers/swagger.py
rest_helpers/type_deserializers.py
rest_helpers/type_serializers.py
rest_helpers/validators.py
rest_helpers/versioning.py
rest_helpers/aiohttp/__init__.py
rest_helpers/aiohttp/binding.py
rest_helpers/aiohttp/responses.py
rest_helpers/aiohttp/routes.py
rest_helpers/common/__init__.py
rest_helpers/common/decorators.py
rest_helpers/flask/__init__.py
rest_helpers/flask/binding.py
rest_helpers/flask/responses.py
rest_helpers/flask/routes.py
rest_helpers/templates/swagger-ui.html
rest_helpers/tests/__init__.py
rest_helpers/tests/conftest.py
rest_helpers/tests/test_binding.py
rest_helpers/tests/test_common.py
rest_helpers/tests/test_responses.py
rest_helpers/tests/test_routes.py
rest_helpers/tests/test_swagger.py
rest_helpers/tests/test_type_deserializers.py
rest_helpers/tests/test_type_serializers.py
rest_helpers/tests/test_validators.py
rest_helpers-1.24.dist-info/LICENSE
rest_helpers-1.24.dist-info/METADATA
rest_helpers-1.24.dist-info/WHEEL
rest_helpers-1.24.dist-info/top_level.txt
rest_helpers-1.24.dist-info/RECORD
