Metadata-Version: 2.1
Name: rest-helpers
Version: 1.24
Summary: A set of method to help creating rest services
Home-page: https://github.com/WillFr/rest-helpers
Author: Guillaume Grosbois
Author-email: grosbois.guillaume@gmail.com
License: UNKNOWN
Platform: UNKNOWN
Classifier: Programming Language :: Python :: 3.5
Classifier: Operating System :: OS Independent
Requires-Dist: setuptools (>=0.5)
Requires-Dist: flask
Requires-Dist: pyyaml
Requires-Dist: requests
Requires-Dist: schematics
Requires-Dist: python-dateutil
Requires-Dist: requests-futures
Requires-Dist: httpretty
Requires-Dist: aiohttp (>=2.3.0)
Requires-Dist: aiotask-context
Requires-Dist: pytest-aiohttp
Requires-Dist: pytest-asyncio
Requires-Dist: cryptography
Requires-Dist: python-jose[cryptography]
Requires-Dist: jinja2
